{
 "date": "2026-07-22",
 "generated_at": "2026-07-22T06:19:05+00:00",
 "underlying": "QQQ",
 "spot": 708.62,
 "data_source": "CBOE",
 "calculation_version": "1.4.0",
 "quote_timestamp": 1784711710,
 "flip_method": "profile",
 "gamma_rank": "total",
 "expiration_used": "2026-07-22",
 "strike_range_pct": 0.15,
 "max_dte": 60,
 "regime": "NEGATIEF (-GEX, momentum)",
 "net_total_gex": -1653919415.0,
 "correlated_symbols": [
  "SPY"
 ],
 "levels": {
  "gamma_flip": 715.39,
  "call_wall": 730.0,
  "put_wall": 700.0,
  "call_wall_secondary": 720.0,
  "put_wall_secondary": 690.0,
  "gamma_levels": [
   690.0,
   710.0,
   705.0,
   720.0,
   695.0,
   680.0,
   715.0,
   660.0,
   740.0,
   725.0
  ],
  "0dte": {
   "flip": 704.38,
   "call_wall": 700.0,
   "put_wall": 716.0
  },
  "session": {
   "ceiling": 714.63,
   "floor": 702.61
  },
  "correlated": [
   750.0,
   740.0,
   751.19,
   745.0,
   755.0,
   752.0,
   735.0,
   730.0,
   746.0,
   760.0
  ]
 },
 "clusters": [
  {
   "lo": 700.0,
   "hi": 700.0,
   "width": 1,
   "center": 700.0,
   "sign": "put",
   "total_gex": 757191076.0,
   "strength_pct": 100.0
  },
  {
   "lo": 690.0,
   "hi": 690.0,
   "width": 1,
   "center": 690.0,
   "sign": "put",
   "total_gex": 656290702.0,
   "strength_pct": 86.7
  },
  {
   "lo": 680.0,
   "hi": 680.0,
   "width": 1,
   "center": 680.0,
   "sign": "put",
   "total_gex": 500040839.0,
   "strength_pct": 66.0
  },
  {
   "lo": 695.0,
   "hi": 695.0,
   "width": 1,
   "center": 695.0,
   "sign": "put",
   "total_gex": 462501534.0,
   "strength_pct": 61.1
  },
  {
   "lo": 730.0,
   "hi": 730.0,
   "width": 1,
   "center": 730.0,
   "sign": "call",
   "total_gex": 450117650.0,
   "strength_pct": 59.4
  },
  {
   "lo": 660.0,
   "hi": 660.0,
   "width": 1,
   "center": 660.0,
   "sign": "put",
   "total_gex": 301653353.0,
   "strength_pct": 39.8
  },
  {
   "lo": 740.0,
   "hi": 740.0,
   "width": 1,
   "center": 740.0,
   "sign": "call",
   "total_gex": 299122756.0,
   "strength_pct": 39.5
  },
  {
   "lo": 733.0,
   "hi": 733.0,
   "width": 1,
   "center": 733.0,
   "sign": "call",
   "total_gex": 247653873.0,
   "strength_pct": 32.7
  }
 ],
 "gamma_profile": {
  "605": {
   "call": 1738969.0,
   "put": 13409007.0,
   "net": -11670038.0
  },
  "610": {
   "call": 13870828.0,
   "put": 27674519.0,
   "net": -13803691.0
  },
  "615": {
   "call": 10020350.0,
   "put": 42329190.0,
   "net": -32308840.0
  },
  "616": {
   "call": 2009.0,
   "put": 54734.0,
   "net": -52725.0
  },
  "617": {
   "call": 4017.0,
   "put": 126038.0,
   "net": -122021.0
  },
  "618": {
   "call": 1105.0,
   "put": 166259.0,
   "net": -165155.0
  },
  "619": {
   "call": 2762.0,
   "put": 37560.0,
   "net": -34798.0
  },
  "620": {
   "call": 6335027.0,
   "put": 73711678.0,
   "net": -67376651.0
  },
  "621": {
   "call": 603.0,
   "put": 61462.0,
   "net": -60860.0
  },
  "622": {
   "call": 2410.0,
   "put": 80744.0,
   "net": -78334.0
  },
  "623": {
   "call": 1306.0,
   "put": 477186.0,
   "net": -475880.0
  },
  "624": {
   "call": 1958.0,
   "put": 91390.0,
   "net": -89432.0
  },
  "625": {
   "call": 9565911.0,
   "put": 31357230.0,
   "net": -21791319.0
  },
  "626": {
   "call": 6327.0,
   "put": 56943.0,
   "net": -50616.0
  },
  "627": {
   "call": 3515.0,
   "put": 145521.0,
   "net": -142006.0
  },
  "628": {
   "call": 2260.0,
   "put": 97165.0,
   "net": -94905.0
  },
  "629": {
   "call": 1506.0,
   "put": 82853.0,
   "net": -81347.0
  },
  "630": {
   "call": 17794919.0,
   "put": 75046573.0,
   "net": -57251654.0
  },
  "631": {
   "call": 4017.0,
   "put": 110070.0,
   "net": -106052.0
  },
  "632": {
   "call": 4268.0,
   "put": 828033.0,
   "net": -823764.0
  },
  "633": {
   "call": 6829.0,
   "put": 258654.0,
   "net": -251824.0
  },
  "634": {
   "call": 3615.0,
   "put": 117501.0,
   "net": -113886.0
  },
  "635": {
   "call": 7997771.0,
   "put": 33658548.0,
   "net": -25660777.0
  },
  "636": {
   "call": 1908.0,
   "put": 330108.0,
   "net": -328200.0
  },
  "637": {
   "call": 7030.0,
   "put": 1267407.0,
   "net": -1260377.0
  },
  "638": {
   "call": 33141.0,
   "put": 310023.0,
   "net": -276881.0
  },
  "639": {
   "call": 39016.0,
   "put": 191919.0,
   "net": -152902.0
  },
  "640": {
   "call": 17280424.0,
   "put": 55965316.0,
   "net": -38684892.0
  },
  "641": {
   "call": 16169.0,
   "put": 228676.0,
   "net": -212507.0
  },
  "642": {
   "call": 26563.0,
   "put": 478441.0,
   "net": -451878.0
  },
  "643": {
   "call": 28923.0,
   "put": 215720.0,
   "net": -186797.0
  },
  "644": {
   "call": 30129.0,
   "put": 271157.0,
   "net": -241028.0
  },
  "645": {
   "call": 18669751.0,
   "put": 47201377.0,
   "net": -28531625.0
  },
  "646": {
   "call": 17625.0,
   "put": 287426.0,
   "net": -269801.0
  },
  "647": {
   "call": 74518.0,
   "put": 354312.0,
   "net": -279794.0
  },
  "648": {
   "call": 11650.0,
   "put": 650927.0,
   "net": -639277.0
  },
  "649": {
   "call": 31635.0,
   "put": 445902.0,
   "net": -414267.0
  },
  "650": {
   "call": 18341400.0,
   "put": 228486398.0,
   "net": -210144998.0
  },
  "651": {
   "call": 14964.0,
   "put": 1752175.0,
   "net": -1737212.0
  },
  "652": {
   "call": 30279.0,
   "put": 2204505.0,
   "net": -2174226.0
  },
  "653": {
   "call": 42280.0,
   "put": 1585916.0,
   "net": -1543636.0
  },
  "654": {
   "call": 73915.0,
   "put": 1237530.0,
   "net": -1163614.0
  },
  "655": {
   "call": 13845369.0,
   "put": 84099546.0,
   "net": -70254177.0
  },
  "656": {
   "call": 51219.0,
   "put": 2966958.0,
   "net": -2915740.0
  },
  "657": {
   "call": 36807.0,
   "put": 2241061.0,
   "net": -2204254.0
  },
  "658": {
   "call": 87222.0,
   "put": 2588845.0,
   "net": -2501623.0
  },
  "659": {
   "call": 234601.0,
   "put": 6827127.0,
   "net": -6592526.0
  },
  "660": {
   "call": 49829389.0,
   "put": 351482741.0,
   "net": -301653353.0
  },
  "661": {
   "call": 410150.0,
   "put": 2780462.0,
   "net": -2370313.0
  },
  "662": {
   "call": 130457.0,
   "put": 2524219.0,
   "net": -2393763.0
  },
  "663": {
   "call": 208540.0,
   "put": 3279441.0,
   "net": -3070901.0
  },
  "664": {
   "call": 56993.0,
   "put": 6406884.0,
   "net": -6349891.0
  },
  "665": {
   "call": 8900974.0,
   "put": 133107681.0,
   "net": -124206707.0
  },
  "666": {
   "call": 143010.0,
   "put": 2211083.0,
   "net": -2068073.0
  },
  "667": {
   "call": 322928.0,
   "put": 2437600.0,
   "net": -2114672.0
  },
  "668": {
   "call": 97265.0,
   "put": 5164483.0,
   "net": -5067218.0
  },
  "669": {
   "call": 349340.0,
   "put": 3101984.0,
   "net": -2752644.0
  },
  "670": {
   "call": 31536043.0,
   "put": 209193539.0,
   "net": -177657495.0
  },
  "671": {
   "call": 176252.0,
   "put": 2310608.0,
   "net": -2134356.0
  },
  "672": {
   "call": 315998.0,
   "put": 3071906.0,
   "net": -2755908.0
  },
  "673": {
   "call": 160786.0,
   "put": 8128479.0,
   "net": -7967693.0
  },
  "674": {
   "call": 171733.0,
   "put": 1789133.0,
   "net": -1617400.0
  },
  "675": {
   "call": 35302311.0,
   "put": 182159753.0,
   "net": -146857442.0
  },
  "676": {
   "call": 225261.0,
   "put": 20033369.0,
   "net": -19808108.0
  },
  "677": {
   "call": 154610.0,
   "put": 3199701.0,
   "net": -3045091.0
  },
  "678": {
   "call": 433148.0,
   "put": 6760894.0,
   "net": -6327746.0
  },
  "679": {
   "call": 252427.0,
   "put": 6015062.0,
   "net": -5762635.0
  },
  "680": {
   "call": 36391056.0,
   "put": 536431895.0,
   "net": -500040839.0
  },
  "681": {
   "call": 361342.0,
   "put": 10586516.0,
   "net": -10225174.0
  },
  "682": {
   "call": 512386.0,
   "put": 43755224.0,
   "net": -43242838.0
  },
  "683": {
   "call": 711385.0,
   "put": 33758425.0,
   "net": -33047040.0
  },
  "684": {
   "call": 645253.0,
   "put": 19887045.0,
   "net": -19241792.0
  },
  "685": {
   "call": 41910604.0,
   "put": 279868260.0,
   "net": -237957656.0
  },
  "686": {
   "call": 3893511.0,
   "put": 18396837.0,
   "net": -14503326.0
  },
  "687": {
   "call": 3874128.0,
   "put": 16188566.0,
   "net": -12314437.0
  },
  "688": {
   "call": 4524704.0,
   "put": 29793308.0,
   "net": -25268604.0
  },
  "689": {
   "call": 6841287.0,
   "put": 14508950.0,
   "net": -7667663.0
  },
  "690": {
   "call": 67620843.0,
   "put": 723911545.0,
   "net": -656290702.0
  },
  "691": {
   "call": 9027514.0,
   "put": 53147595.0,
   "net": -44120081.0
  },
  "692": {
   "call": 6614018.0,
   "put": 125928151.0,
   "net": -119314133.0
  },
  "693": {
   "call": 8328382.0,
   "put": 37396345.0,
   "net": -29067964.0
  },
  "694": {
   "call": 14112458.0,
   "put": 59833469.0,
   "net": -45721011.0
  },
  "695": {
   "call": 61177654.0,
   "put": 523679188.0,
   "net": -462501534.0
  },
  "696": {
   "call": 33858552.0,
   "put": 42603611.0,
   "net": -8745059.0
  },
  "697": {
   "call": 28471619.0,
   "put": 32913570.0,
   "net": -4441951.0
  },
  "698": {
   "call": 30285056.0,
   "put": 83314346.0,
   "net": -53029290.0
  },
  "699": {
   "call": 38165627.0,
   "put": 74552767.0,
   "net": -36387140.0
  },
  "700": {
   "call": 380820104.0,
   "put": 1138011180.0,
   "net": -757191076.0
  },
  "701": {
   "call": 57239201.0,
   "put": 107115741.0,
   "net": -49876540.0
  },
  "702": {
   "call": 38810629.0,
   "put": 104115190.0,
   "net": -65304561.0
  },
  "703": {
   "call": 47241397.0,
   "put": 70080788.0,
   "net": -22839390.0
  },
  "704": {
   "call": 32959366.0,
   "put": 42809138.0,
   "net": -9849772.0
  },
  "705": {
   "call": 266561790.0,
   "put": 373098411.0,
   "net": -106536620.0
  },
  "706": {
   "call": 54645435.0,
   "put": 38405701.0,
   "net": 16239734.0
  },
  "707": {
   "call": 72203594.0,
   "put": 48844788.0,
   "net": 23358806.0
  },
  "708": {
   "call": 57541742.0,
   "put": 61752657.0,
   "net": -4210915.0
  },
  "709": {
   "call": 46983547.0,
   "put": 33103581.0,
   "net": 13879967.0
  },
  "710": {
   "call": 341374617.0,
   "put": 329640706.0,
   "net": 11733911.0
  },
  "711": {
   "call": 56125500.0,
   "put": 43419693.0,
   "net": 12705807.0
  },
  "712": {
   "call": 58519162.0,
   "put": 54479929.0,
   "net": 4039233.0
  },
  "712.5": {
   "call": 489689.0,
   "put": 252176.0,
   "net": 237513.0
  },
  "713": {
   "call": 69737473.0,
   "put": 28073119.0,
   "net": 41664354.0
  },
  "714": {
   "call": 55934736.0,
   "put": 36013395.0,
   "net": 19921341.0
  },
  "715": {
   "call": 305201038.0,
   "put": 180207173.0,
   "net": 124993865.0
  },
  "716": {
   "call": 57028804.0,
   "put": 111684382.0,
   "net": -54655579.0
  },
  "717": {
   "call": 40967380.0,
   "put": 23735363.0,
   "net": 17232017.0
  },
  "717.5": {
   "call": 396943.0,
   "put": 214666.0,
   "net": 182278.0
  },
  "718": {
   "call": 44512555.0,
   "put": 30720413.0,
   "net": 13792142.0
  },
  "719": {
   "call": 38331635.0,
   "put": 18777310.0,
   "net": 19554325.0
  },
  "720": {
   "call": 401652733.0,
   "put": 233462478.0,
   "net": 168190255.0
  },
  "721": {
   "call": 47026782.0,
   "put": 15615370.0,
   "net": 31411411.0
  },
  "722": {
   "call": 53686595.0,
   "put": 14244120.0,
   "net": 39442475.0
  },
  "722.5": {
   "call": 1751171.0,
   "put": 226567.0,
   "net": 1524604.0
  },
  "723": {
   "call": 41621923.0,
   "put": 13590230.0,
   "net": 28031692.0
  },
  "724": {
   "call": 35400731.0,
   "put": 7757496.0,
   "net": 27643235.0
  },
  "725": {
   "call": 275333815.0,
   "put": 89182281.0,
   "net": 186151534.0
  },
  "726": {
   "call": 19243750.0,
   "put": 5406968.0,
   "net": 13836782.0
  },
  "727": {
   "call": 13318170.0,
   "put": 4640146.0,
   "net": 8678023.0
  },
  "727.5": {
   "call": 304901.0,
   "put": 19081.0,
   "net": 285819.0
  },
  "728": {
   "call": 26028446.0,
   "put": 7359297.0,
   "net": 18669149.0
  },
  "729": {
   "call": 15752053.0,
   "put": 2485102.0,
   "net": 13266951.0
  },
  "730": {
   "call": 519315169.0,
   "put": 69197519.0,
   "net": 450117650.0
  },
  "731": {
   "call": 16358692.0,
   "put": 1377728.0,
   "net": 14980964.0
  },
  "732": {
   "call": 17744403.0,
   "put": 2228608.0,
   "net": 15515795.0
  },
  "732.5": {
   "call": 290489.0,
   "put": 36958.0,
   "net": 253532.0
  },
  "733": {
   "call": 249064742.0,
   "put": 1410869.0,
   "net": 247653873.0
  },
  "734": {
   "call": 9522175.0,
   "put": 1839849.0,
   "net": 7682325.0
  },
  "735": {
   "call": 191427894.0,
   "put": 46927458.0,
   "net": 144500436.0
  },
  "736": {
   "call": 233930575.0,
   "put": 4453902.0,
   "net": 229476673.0
  },
  "737": {
   "call": 19848581.0,
   "put": 8101012.0,
   "net": 11747569.0
  },
  "737.5": {
   "call": 506159.0,
   "put": 0.0,
   "net": 506159.0
  },
  "738": {
   "call": 7479159.0,
   "put": 1581598.0,
   "net": 5897561.0
  },
  "739": {
   "call": 7478104.0,
   "put": 811964.0,
   "net": 6666140.0
  },
  "740": {
   "call": 333077318.0,
   "put": 33954561.0,
   "net": 299122756.0
  },
  "741": {
   "call": 5177288.0,
   "put": 768328.0,
   "net": 4408960.0
  },
  "742": {
   "call": 18045639.0,
   "put": 2901730.0,
   "net": 15143909.0
  },
  "742.5": {
   "call": 152752.0,
   "put": 20588.0,
   "net": 132164.0
  },
  "743": {
   "call": 47295026.0,
   "put": 1012269.0,
   "net": 46282757.0
  },
  "744": {
   "call": 3785249.0,
   "put": 775559.0,
   "net": 3009690.0
  },
  "745": {
   "call": 92074269.0,
   "put": 20427149.0,
   "net": 71647120.0
  },
  "746": {
   "call": 12139491.0,
   "put": 206933.0,
   "net": 11932558.0
  },
  "747": {
   "call": 5963392.0,
   "put": 712942.0,
   "net": 5250450.0
  },
  "748": {
   "call": 21381621.0,
   "put": 149337.0,
   "net": 21232284.0
  },
  "749": {
   "call": 5413496.0,
   "put": 148383.0,
   "net": 5265113.0
  },
  "750": {
   "call": 213391549.0,
   "put": 19361352.0,
   "net": 194030197.0
  },
  "751": {
   "call": 3530663.0,
   "put": 61261.0,
   "net": 3469402.0
  },
  "752": {
   "call": 5974690.0,
   "put": 19433.0,
   "net": 5955257.0
  },
  "753": {
   "call": 3924543.0,
   "put": 208791.0,
   "net": 3715753.0
  },
  "754": {
   "call": 2226147.0,
   "put": 66283.0,
   "net": 2159865.0
  },
  "755": {
   "call": 55974907.0,
   "put": 5844836.0,
   "net": 50130071.0
  },
  "756": {
   "call": 2079723.0,
   "put": 68442.0,
   "net": 2011281.0
  },
  "757": {
   "call": 2015599.0,
   "put": 18981.0,
   "net": 1996618.0
  },
  "758": {
   "call": 1675348.0,
   "put": 74719.0,
   "net": 1600629.0
  },
  "759": {
   "call": 1983763.0,
   "put": 0.0,
   "net": 1983763.0
  },
  "760": {
   "call": 97726935.0,
   "put": 5145101.0,
   "net": 92581835.0
  },
  "761": {
   "call": 1567035.0,
   "put": 33141.0,
   "net": 1533894.0
  },
  "762": {
   "call": 386348.0,
   "put": 65178.0,
   "net": 321170.0
  },
  "763": {
   "call": 445601.0,
   "put": 0.0,
   "net": 445601.0
  },
  "764": {
   "call": 524789.0,
   "put": 0.0,
   "net": 524789.0
  },
  "765": {
   "call": 36854132.0,
   "put": 1236224.0,
   "net": 35617908.0
  },
  "766": {
   "call": 1019751.0,
   "put": 28120.0,
   "net": 991631.0
  },
  "767": {
   "call": 676938.0,
   "put": 0.0,
   "net": 676938.0
  },
  "768": {
   "call": 462674.0,
   "put": 0.0,
   "net": 462674.0
  },
  "769": {
   "call": 468649.0,
   "put": 0.0,
   "net": 468649.0
  },
  "770": {
   "call": 60272894.0,
   "put": 483161.0,
   "net": 59789733.0
  },
  "771": {
   "call": 735789.0,
   "put": 0.0,
   "net": 735789.0
  },
  "772": {
   "call": 1273383.0,
   "put": 0.0,
   "net": 1273383.0
  },
  "773": {
   "call": 502996.0,
   "put": 2561.0,
   "net": 500435.0
  },
  "774": {
   "call": 424059.0,
   "put": 33292.0,
   "net": 390767.0
  },
  "775": {
   "call": 24780421.0,
   "put": 596947.0,
   "net": 24183475.0
  },
  "780": {
   "call": 30187841.0,
   "put": 695768.0,
   "net": 29492073.0
  },
  "785": {
   "call": 24340444.0,
   "put": 97315.0,
   "net": 24243129.0
  },
  "790": {
   "call": 72276756.0,
   "put": 138190.0,
   "net": 72138567.0
  },
  "795": {
   "call": 6487277.0,
   "put": 4017.0,
   "net": 6483260.0
  },
  "800": {
   "call": 68725255.0,
   "put": 58299.0,
   "net": 68666956.0
  },
  "805": {
   "call": 36972386.0,
   "put": 0.0,
   "net": 36972386.0
  },
  "810": {
   "call": 10781949.0,
   "put": 0.0,
   "net": 10781949.0
  }
 },
 "migration": {
  "vs_date": "2026-07-21",
  "spot": {
   "prev": 709.05,
   "now": 708.62,
   "delta": -0.43
  },
  "net_total_gex": {
   "prev": -205130064.0,
   "now": -1653919415.0,
   "delta": -1448789351.0
  },
  "regime_changed": false,
  "gamma_flip": {
   "prev": 714.39,
   "now": 715.39,
   "delta": 1.0
  },
  "call_wall": {
   "prev": 709.0,
   "now": 730.0,
   "delta": 21.0
  },
  "put_wall": {
   "prev": 700.0,
   "now": 700.0,
   "delta": 0.0
  }
 }
}