{
 "date": "2026-07-24",
 "generated_at": "2026-07-24T10:15:09+00:00",
 "underlying": "SPY",
 "spot": 740.56,
 "data_source": "CBOE",
 "calculation_version": "1.4.0",
 "quote_timestamp": 1784902252,
 "flip_method": "profile",
 "gamma_rank": "total",
 "expiration_used": "2026-07-24",
 "strike_range_pct": 0.15,
 "max_dte": 60,
 "regime": "NEGATIEF (-GEX, momentum)",
 "net_total_gex": -10437250218.0,
 "correlated_symbols": [
  "QQQ"
 ],
 "levels": {
  "gamma_flip": 746.49,
  "call_wall": 745.0,
  "put_wall": 740.0,
  "call_wall_secondary": 750.0,
  "put_wall_secondary": 730.0,
  "gamma_levels": [
   750.0,
   730.0,
   735.0,
   720.0,
   725.0,
   743.0,
   742.0,
   755.0,
   746.0,
   710.0
  ],
  "0dte": {
   "flip": 740.71,
   "call_wall": 745.0,
   "put_wall": 740.0
  },
  "session": {
   "ceiling": 744.89,
   "floor": 736.23
  },
  "correlated": [
   700.0,
   700.0,
   707.06,
   690.0,
   695.0,
   680.0,
   705.0,
   685.0,
   710.0,
   660.0
  ]
 },
 "clusters": [
  {
   "lo": 740.0,
   "hi": 740.0,
   "width": 1,
   "center": 740.0,
   "sign": "put",
   "total_gex": 1761369383.0,
   "strength_pct": 100.0
  },
  {
   "lo": 735.0,
   "hi": 735.0,
   "width": 1,
   "center": 735.0,
   "sign": "put",
   "total_gex": 1294010267.0,
   "strength_pct": 73.5
  },
  {
   "lo": 730.0,
   "hi": 730.0,
   "width": 1,
   "center": 730.0,
   "sign": "put",
   "total_gex": 1262683119.0,
   "strength_pct": 71.7
  },
  {
   "lo": 720.0,
   "hi": 720.0,
   "width": 1,
   "center": 720.0,
   "sign": "put",
   "total_gex": 1152236680.0,
   "strength_pct": 65.4
  },
  {
   "lo": 725.0,
   "hi": 725.0,
   "width": 1,
   "center": 725.0,
   "sign": "put",
   "total_gex": 920269592.0,
   "strength_pct": 52.2
  },
  {
   "lo": 710.0,
   "hi": 710.0,
   "width": 1,
   "center": 710.0,
   "sign": "put",
   "total_gex": 733480394.0,
   "strength_pct": 41.6
  },
  {
   "lo": 760.0,
   "hi": 760.0,
   "width": 1,
   "center": 760.0,
   "sign": "call",
   "total_gex": 569944481.0,
   "strength_pct": 32.4
  },
  {
   "lo": 715.0,
   "hi": 715.0,
   "width": 1,
   "center": 715.0,
   "sign": "put",
   "total_gex": 505231601.0,
   "strength_pct": 28.7
  }
 ],
 "gamma_profile": {
  "630": {
   "call": 1427726.0,
   "put": 101934216.0,
   "net": -100506490.0
  },
  "631": {
   "call": 1810.0,
   "put": 1451637.0,
   "net": -1449827.0
  },
  "632": {
   "call": 6636.0,
   "put": 797580.0,
   "net": -790944.0
  },
  "633": {
   "call": 9159.0,
   "put": 662283.0,
   "net": -653124.0
  },
  "634": {
   "call": 28628.0,
   "put": 988818.0,
   "net": -960190.0
  },
  "635": {
   "call": 1054245.0,
   "put": 18010906.0,
   "net": -16956660.0
  },
  "636": {
   "call": 8665.0,
   "put": 391907.0,
   "net": -383242.0
  },
  "637": {
   "call": 157838.0,
   "put": 688608.0,
   "net": -530770.0
  },
  "638": {
   "call": 133213.0,
   "put": 427281.0,
   "net": -294068.0
  },
  "639": {
   "call": 27641.0,
   "put": 373809.0,
   "net": -346168.0
  },
  "640": {
   "call": 5942888.0,
   "put": 23975511.0,
   "net": -18032623.0
  },
  "641": {
   "call": 1575198.0,
   "put": 1876176.0,
   "net": -300978.0
  },
  "642": {
   "call": 1438201.0,
   "put": 1437213.0,
   "net": 987.0
  },
  "643": {
   "call": 1465293.0,
   "put": 1654336.0,
   "net": -189044.0
  },
  "644": {
   "call": 1216745.0,
   "put": 1613917.0,
   "net": -397172.0
  },
  "645": {
   "call": 2342725.0,
   "put": 24757297.0,
   "net": -22414572.0
  },
  "646": {
   "call": 725627.0,
   "put": 904250.0,
   "net": -178623.0
  },
  "647": {
   "call": 354066.0,
   "put": 657841.0,
   "net": -303775.0
  },
  "648": {
   "call": 1052874.0,
   "put": 1361146.0,
   "net": -308272.0
  },
  "649": {
   "call": 944834.0,
   "put": 1759470.0,
   "net": -814637.0
  },
  "650": {
   "call": 5902194.0,
   "put": 107719430.0,
   "net": -101817236.0
  },
  "651": {
   "call": 357740.0,
   "put": 2897790.0,
   "net": -2540049.0
  },
  "652": {
   "call": 387246.0,
   "put": 4460703.0,
   "net": -4073457.0
  },
  "653": {
   "call": 412199.0,
   "put": 1466938.0,
   "net": -1054739.0
  },
  "654": {
   "call": 267195.0,
   "put": 6216773.0,
   "net": -5949578.0
  },
  "655": {
   "call": 2150226.0,
   "put": 53058707.0,
   "net": -50908481.0
  },
  "656": {
   "call": 78700.0,
   "put": 2660484.0,
   "net": -2581785.0
  },
  "657": {
   "call": 197489.0,
   "put": 5236017.0,
   "net": -5038528.0
  },
  "658": {
   "call": 126797.0,
   "put": 1592474.0,
   "net": -1465677.0
  },
  "659": {
   "call": 110125.0,
   "put": 7776341.0,
   "net": -7666216.0
  },
  "660": {
   "call": 7759011.0,
   "put": 109605917.0,
   "net": -101846906.0
  },
  "661": {
   "call": 209116.0,
   "put": 1958769.0,
   "net": -1749653.0
  },
  "662": {
   "call": 133268.0,
   "put": 3003527.0,
   "net": -2870259.0
  },
  "663": {
   "call": 114622.0,
   "put": 2140683.0,
   "net": -2026062.0
  },
  "664": {
   "call": 248658.0,
   "put": 2379305.0,
   "net": -2130647.0
  },
  "665": {
   "call": 9414992.0,
   "put": 173056533.0,
   "net": -163641540.0
  },
  "666": {
   "call": 229134.0,
   "put": 3902512.0,
   "net": -3673378.0
  },
  "667": {
   "call": 277615.0,
   "put": 3360993.0,
   "net": -3083378.0
  },
  "668": {
   "call": 361031.0,
   "put": 3985270.0,
   "net": -3624239.0
  },
  "669": {
   "call": 333445.0,
   "put": 3318216.0,
   "net": -2984771.0
  },
  "670": {
   "call": 11853144.0,
   "put": 212948224.0,
   "net": -201095081.0
  },
  "671": {
   "call": 208897.0,
   "put": 4426591.0,
   "net": -4217694.0
  },
  "672": {
   "call": 90930.0,
   "put": 5684797.0,
   "net": -5593867.0
  },
  "673": {
   "call": 272789.0,
   "put": 3961687.0,
   "net": -3688899.0
  },
  "674": {
   "call": 414832.0,
   "put": 5207115.0,
   "net": -4792283.0
  },
  "675": {
   "call": 19153393.0,
   "put": 105943672.0,
   "net": -86790278.0
  },
  "676": {
   "call": 242954.0,
   "put": 8404128.0,
   "net": -8161174.0
  },
  "677": {
   "call": 853027.0,
   "put": 7694790.0,
   "net": -6841763.0
  },
  "678": {
   "call": 619451.0,
   "put": 7721827.0,
   "net": -7102376.0
  },
  "679": {
   "call": 869699.0,
   "put": 5659350.0,
   "net": -4789651.0
  },
  "680": {
   "call": 16239315.0,
   "put": 111270893.0,
   "net": -95031577.0
  },
  "681": {
   "call": 1068175.0,
   "put": 26984687.0,
   "net": -25916511.0
  },
  "682": {
   "call": 652685.0,
   "put": 25523123.0,
   "net": -24870438.0
  },
  "683": {
   "call": 1169580.0,
   "put": 16306991.0,
   "net": -15137411.0
  },
  "684": {
   "call": 393279.0,
   "put": 9976145.0,
   "net": -9582866.0
  },
  "685": {
   "call": 16356405.0,
   "put": 92772104.0,
   "net": -76415700.0
  },
  "686": {
   "call": 396405.0,
   "put": 11508675.0,
   "net": -11112271.0
  },
  "687": {
   "call": 303391.0,
   "put": 11452352.0,
   "net": -11148961.0
  },
  "688": {
   "call": 235550.0,
   "put": 11594340.0,
   "net": -11358790.0
  },
  "689": {
   "call": 478450.0,
   "put": 10211366.0,
   "net": -9732917.0
  },
  "690": {
   "call": 32798858.0,
   "put": 179773199.0,
   "net": -146974341.0
  },
  "691": {
   "call": 408141.0,
   "put": 14134334.0,
   "net": -13726194.0
  },
  "692": {
   "call": 665354.0,
   "put": 13631260.0,
   "net": -12965906.0
  },
  "693": {
   "call": 1081722.0,
   "put": 28665128.0,
   "net": -27583407.0
  },
  "694": {
   "call": 538119.0,
   "put": 13556290.0,
   "net": -13018172.0
  },
  "695": {
   "call": 33159121.0,
   "put": 111711500.0,
   "net": -78552379.0
  },
  "696": {
   "call": 1723438.0,
   "put": 20948731.0,
   "net": -19225292.0
  },
  "697": {
   "call": 1098668.0,
   "put": 20953063.0,
   "net": -19854395.0
  },
  "698": {
   "call": 554407.0,
   "put": 34459940.0,
   "net": -33905533.0
  },
  "699": {
   "call": 1076512.0,
   "put": 19226060.0,
   "net": -18149549.0
  },
  "700": {
   "call": 76241464.0,
   "put": 417836570.0,
   "net": -341595106.0
  },
  "701": {
   "call": 2003302.0,
   "put": 22834395.0,
   "net": -20831093.0
  },
  "702": {
   "call": 1296157.0,
   "put": 64941411.0,
   "net": -63645253.0
  },
  "703": {
   "call": 1274714.0,
   "put": 65366334.0,
   "net": -64091620.0
  },
  "704": {
   "call": 1133822.0,
   "put": 52437337.0,
   "net": -51303514.0
  },
  "705": {
   "call": 37342209.0,
   "put": 229055587.0,
   "net": -191713378.0
  },
  "706": {
   "call": 1864714.0,
   "put": 135543488.0,
   "net": -133678774.0
  },
  "707": {
   "call": 1401840.0,
   "put": 29083689.0,
   "net": -27681850.0
  },
  "708": {
   "call": 3012028.0,
   "put": 86187171.0,
   "net": -83175143.0
  },
  "709": {
   "call": 4230089.0,
   "put": 75070403.0,
   "net": -70840314.0
  },
  "710": {
   "call": 47069038.0,
   "put": 780549433.0,
   "net": -733480394.0
  },
  "711": {
   "call": 4296284.0,
   "put": 36454796.0,
   "net": -32158512.0
  },
  "712": {
   "call": 3191090.0,
   "put": 100301378.0,
   "net": -97110288.0
  },
  "713": {
   "call": 2972431.0,
   "put": 47425627.0,
   "net": -44453196.0
  },
  "714": {
   "call": 6857119.0,
   "put": 219315486.0,
   "net": -212458367.0
  },
  "715": {
   "call": 60662841.0,
   "put": 565894442.0,
   "net": -505231601.0
  },
  "716": {
   "call": 6686119.0,
   "put": 204776576.0,
   "net": -198090457.0
  },
  "717": {
   "call": 5182929.0,
   "put": 195137605.0,
   "net": -189954676.0
  },
  "718": {
   "call": 2156807.0,
   "put": 184028515.0,
   "net": -181871708.0
  },
  "719": {
   "call": 8939011.0,
   "put": 93143501.0,
   "net": -84204490.0
  },
  "720": {
   "call": 125257151.0,
   "put": 1277493831.0,
   "net": -1152236680.0
  },
  "721": {
   "call": 5119366.0,
   "put": 147169691.0,
   "net": -142050325.0
  },
  "722": {
   "call": 6553179.0,
   "put": 108003462.0,
   "net": -101450282.0
  },
  "723": {
   "call": 19266808.0,
   "put": 125183497.0,
   "net": -105916689.0
  },
  "724": {
   "call": 7116197.0,
   "put": 241291370.0,
   "net": -234175173.0
  },
  "725": {
   "call": 125363382.0,
   "put": 1045632974.0,
   "net": -920269592.0
  },
  "726": {
   "call": 17467522.0,
   "put": 142126173.0,
   "net": -124658650.0
  },
  "727": {
   "call": 11202158.0,
   "put": 174585827.0,
   "net": -163383669.0
  },
  "728": {
   "call": 14803583.0,
   "put": 289206031.0,
   "net": -274402449.0
  },
  "729": {
   "call": 12677378.0,
   "put": 227173927.0,
   "net": -214496549.0
  },
  "730": {
   "call": 306557725.0,
   "put": 1569240844.0,
   "net": -1262683119.0
  },
  "731": {
   "call": 16909660.0,
   "put": 378711582.0,
   "net": -361801922.0
  },
  "732": {
   "call": 39758807.0,
   "put": 369768019.0,
   "net": -330009212.0
  },
  "733": {
   "call": 64911521.0,
   "put": 529140478.0,
   "net": -464228956.0
  },
  "734": {
   "call": 74162972.0,
   "put": 361829179.0,
   "net": -287666207.0
  },
  "735": {
   "call": 246246537.0,
   "put": 1540256804.0,
   "net": -1294010267.0
  },
  "736": {
   "call": 127257162.0,
   "put": 357168354.0,
   "net": -229911192.0
  },
  "737": {
   "call": 253247947.0,
   "put": 456711200.0,
   "net": -203463252.0
  },
  "738": {
   "call": 295769028.0,
   "put": 487291059.0,
   "net": -191522031.0
  },
  "739": {
   "call": 388755129.0,
   "put": 430682151.0,
   "net": -41927022.0
  },
  "740": {
   "call": 867998319.0,
   "put": 2629367702.0,
   "net": -1761369383.0
  },
  "741": {
   "call": 414310774.0,
   "put": 346246717.0,
   "net": 68064057.0
  },
  "742": {
   "call": 601828779.0,
   "put": 427023799.0,
   "net": 174804979.0
  },
  "743": {
   "call": 466582266.0,
   "put": 700989479.0,
   "net": -234407213.0
  },
  "744": {
   "call": 424018408.0,
   "put": 341711483.0,
   "net": 82306925.0
  },
  "745": {
   "call": 1010643361.0,
   "put": 1215807676.0,
   "net": -205164315.0
  },
  "746": {
   "call": 513019569.0,
   "put": 333708257.0,
   "net": 179311312.0
  },
  "747": {
   "call": 434441248.0,
   "put": 287952542.0,
   "net": 146488707.0
  },
  "748": {
   "call": 551064864.0,
   "put": 193580121.0,
   "net": 357484743.0
  },
  "749": {
   "call": 286754882.0,
   "put": 134092454.0,
   "net": 152662428.0
  },
  "750": {
   "call": 963580574.0,
   "put": 1115551543.0,
   "net": -151970969.0
  },
  "751": {
   "call": 174145877.0,
   "put": 95574522.0,
   "net": 78571355.0
  },
  "752": {
   "call": 263548488.0,
   "put": 79935518.0,
   "net": 183612970.0
  },
  "753": {
   "call": 267246546.0,
   "put": 75114387.0,
   "net": 192132159.0
  },
  "754": {
   "call": 185852152.0,
   "put": 72135649.0,
   "net": 113716502.0
  },
  "755": {
   "call": 644064402.0,
   "put": 301652685.0,
   "net": 342411717.0
  },
  "756": {
   "call": 135059938.0,
   "put": 71901854.0,
   "net": 63158084.0
  },
  "757": {
   "call": 142986658.0,
   "put": 58512670.0,
   "net": 84473988.0
  },
  "758": {
   "call": 153345935.0,
   "put": 31757610.0,
   "net": 121588325.0
  },
  "759": {
   "call": 91368455.0,
   "put": 20497757.0,
   "net": 70870697.0
  },
  "760": {
   "call": 663260134.0,
   "put": 93315652.0,
   "net": 569944481.0
  },
  "761": {
   "call": 92211171.0,
   "put": 14430980.0,
   "net": 77780191.0
  },
  "762": {
   "call": 79391366.0,
   "put": 8958864.0,
   "net": 70432503.0
  },
  "763": {
   "call": 66054832.0,
   "put": 3402399.0,
   "net": 62652432.0
  },
  "764": {
   "call": 53423796.0,
   "put": 27762140.0,
   "net": 25661656.0
  },
  "765": {
   "call": 284170355.0,
   "put": 34450946.0,
   "net": 249719409.0
  },
  "766": {
   "call": 49965402.0,
   "put": 6851031.0,
   "net": 43114371.0
  },
  "767": {
   "call": 49262481.0,
   "put": 13267762.0,
   "net": 35994719.0
  },
  "768": {
   "call": 69770165.0,
   "put": 3373113.0,
   "net": 66397051.0
  },
  "769": {
   "call": 39814199.0,
   "put": 15565789.0,
   "net": 24248409.0
  },
  "770": {
   "call": 276757294.0,
   "put": 30396409.0,
   "net": 246360884.0
  },
  "771": {
   "call": 44375484.0,
   "put": 3863628.0,
   "net": 40511855.0
  },
  "772": {
   "call": 33323595.0,
   "put": 2319471.0,
   "net": 31004124.0
  },
  "773": {
   "call": 30407981.0,
   "put": 2728051.0,
   "net": 27679930.0
  },
  "774": {
   "call": 51342617.0,
   "put": 9015900.0,
   "net": 42326717.0
  },
  "775": {
   "call": 179975295.0,
   "put": 22814487.0,
   "net": 157160808.0
  },
  "776": {
   "call": 46007060.0,
   "put": 7033110.0,
   "net": 38973950.0
  },
  "777": {
   "call": 30668430.0,
   "put": 1464032.0,
   "net": 29204399.0
  },
  "778": {
   "call": 25026192.0,
   "put": 565101.0,
   "net": 24461090.0
  },
  "779": {
   "call": 20480043.0,
   "put": 3557769.0,
   "net": 16922274.0
  },
  "780": {
   "call": 219178434.0,
   "put": 6712059.0,
   "net": 212466374.0
  },
  "781": {
   "call": 17439607.0,
   "put": 1290563.0,
   "net": 16149044.0
  },
  "782": {
   "call": 16088607.0,
   "put": 2188452.0,
   "net": 13900155.0
  },
  "783": {
   "call": 12145456.0,
   "put": 3306918.0,
   "net": 8838538.0
  },
  "784": {
   "call": 14918588.0,
   "put": 1494524.0,
   "net": 13424064.0
  },
  "785": {
   "call": 80900095.0,
   "put": 672210.0,
   "net": 80227885.0
  },
  "786": {
   "call": 11522276.0,
   "put": 0.0,
   "net": 11522276.0
  },
  "787": {
   "call": 8388168.0,
   "put": 186905.0,
   "net": 8201264.0
  },
  "788": {
   "call": 7639234.0,
   "put": 1536.0,
   "net": 7637698.0
  },
  "789": {
   "call": 11041194.0,
   "put": 0.0,
   "net": 11041194.0
  },
  "790": {
   "call": 66851206.0,
   "put": 0.0,
   "net": 66851206.0
  },
  "791": {
   "call": 8076441.0,
   "put": 0.0,
   "net": 8076441.0
  },
  "792": {
   "call": 5068856.0,
   "put": 0.0,
   "net": 5068856.0
  },
  "793": {
   "call": 6073304.0,
   "put": 0.0,
   "net": 6073304.0
  },
  "794": {
   "call": 4406244.0,
   "put": 0.0,
   "net": 4406244.0
  },
  "795": {
   "call": 30501927.0,
   "put": 0.0,
   "net": 30501927.0
  },
  "796": {
   "call": 5898958.0,
   "put": 0.0,
   "net": 5898958.0
  },
  "797": {
   "call": 27244094.0,
   "put": 0.0,
   "net": 27244094.0
  },
  "798": {
   "call": 3539178.0,
   "put": 0.0,
   "net": 3539178.0
  },
  "799": {
   "call": 5263494.0,
   "put": 0.0,
   "net": 5263494.0
  },
  "800": {
   "call": 68477517.0,
   "put": 110.0,
   "net": 68477408.0
  },
  "801": {
   "call": 2070868.0,
   "put": 0.0,
   "net": 2070868.0
  },
  "802": {
   "call": 343865.0,
   "put": 0.0,
   "net": 343865.0
  },
  "803": {
   "call": 1984875.0,
   "put": 0.0,
   "net": 1984875.0
  },
  "804": {
   "call": 291709.0,
   "put": 0.0,
   "net": 291709.0
  },
  "805": {
   "call": 12831377.0,
   "put": 0.0,
   "net": 12831377.0
  },
  "806": {
   "call": 381158.0,
   "put": 0.0,
   "net": 381158.0
  },
  "807": {
   "call": 142153.0,
   "put": 0.0,
   "net": 142153.0
  },
  "808": {
   "call": 188221.0,
   "put": 0.0,
   "net": 188221.0
  },
  "809": {
   "call": 61040.0,
   "put": 0.0,
   "net": 61040.0
  },
  "810": {
   "call": 15385740.0,
   "put": 0.0,
   "net": 15385740.0
  },
  "811": {
   "call": 257378.0,
   "put": 0.0,
   "net": 257378.0
  },
  "812": {
   "call": 608098.0,
   "put": 0.0,
   "net": 608098.0
  },
  "813": {
   "call": 47384.0,
   "put": 0.0,
   "net": 47384.0
  },
  "814": {
   "call": 495999.0,
   "put": 0.0,
   "net": 495999.0
  },
  "815": {
   "call": 12381061.0,
   "put": 0.0,
   "net": 12381061.0
  },
  "816": {
   "call": 186740.0,
   "put": 0.0,
   "net": 186740.0
  },
  "817": {
   "call": 122080.0,
   "put": 0.0,
   "net": 122080.0
  },
  "818": {
   "call": 130526.0,
   "put": 0.0,
   "net": 130526.0
  },
  "819": {
   "call": 32083.0,
   "put": 0.0,
   "net": 32083.0
  },
  "820": {
   "call": 7392660.0,
   "put": 0.0,
   "net": 7392660.0
  },
  "821": {
   "call": 80290.0,
   "put": 0.0,
   "net": 80290.0
  },
  "822": {
   "call": 238238.0,
   "put": 0.0,
   "net": 238238.0
  },
  "823": {
   "call": 129703.0,
   "put": 0.0,
   "net": 129703.0
  },
  "824": {
   "call": 178788.0,
   "put": 0.0,
   "net": 178788.0
  },
  "825": {
   "call": 8922229.0,
   "put": 0.0,
   "net": 8922229.0
  },
  "830": {
   "call": 3783229.0,
   "put": 0.0,
   "net": 3783229.0
  },
  "835": {
   "call": 3240668.0,
   "put": 0.0,
   "net": 3240668.0
  },
  "840": {
   "call": 3242916.0,
   "put": 0.0,
   "net": 3242916.0
  },
  "845": {
   "call": 2127686.0,
   "put": 0.0,
   "net": 2127686.0
  },
  "850": {
   "call": 3068516.0,
   "put": 0.0,
   "net": 3068516.0
  }
 },
 "migration": null
}